fw_gear_qc_reporter/__init__.py
fw_gear_qc_reporter/dataviews.py
fw_gear_qc_reporter/main.py
fw_gear_qc_reporter/parser.py
fw_gear_qc_reporter/process.py
fw_gear_qc_reporter/qc_config.py
fw_gear_qc_reporter-0.3.3.dist-info/LICENSE
fw_gear_qc_reporter-0.3.3.dist-info/METADATA
fw_gear_qc_reporter-0.3.3.dist-info/WHEEL
fw_gear_qc_reporter-0.3.3.dist-info/RECORD
