Metadata-Version: 2.1
Name: fw-gear-qc-reporter
Version: 0.3.3
Summary: Gear to report on metadata qc results
Home-page: https://gitlab.com/flywheel-io/scientific-solutions/gears/metadata-error-reporter
License: MIT
Keywords: Flywheel,Gears,Errors,QC,Report,Reporter
Author: Flywheel
Author-email: support@flywheel.io
Requires-Python: >=3.11,<4.0
Classifier: License :: OSI Approved :: MIT License
Classifier: Programming Language :: Python :: 3
Classifier: Programming Language :: Python :: 3.11
Classifier: Programming Language :: Python :: 3.12
Classifier: Programming Language :: Python :: 3.13
Classifier: Topic :: Scientific/Engineering
Requires-Dist: backoff (>=2.2.1,<3.0.0)
Requires-Dist: fw-client (>=0.8.6,<0.9.0)
Requires-Dist: fw-gear (>=0.2.1,<0.3.0)
Requires-Dist: pandas (>=2.2.3,<3.0.0)
Requires-Dist: ruamel-yaml (>=0.17.21,<0.18.0)
Project-URL: Repository, https://gitlab.com/flywheel-io/scientific-solutions/gears/metadata-error-reporter
